{
  "name": "DF-90 Mortar Trooper",
  "title": "None",
  "faction": "Galactic Empire",
  "rank": "Corps",
  "unit_type": "Emplacement Trooper",
  "squad_size": 1,
  "stats": {
    "health": 3,
    "courage": 2,
    "speed": 1,
    "defense_die": "Red",
    "surges": {
      "attack": "None",
      "defense": "None"
    }
  },
  "keywords": [
    {
      "ref": "keywords/detachment_shoretroopers"
    },
    {
      "ref": "keywords/fire_support"
    },
    {
      "ref": "keywords/full_pivot"
    },
    {
      "ref": "keywords/prepared_position"
    },
    {
      "ref": "keywords/reposition"
    },
    {
      "ref": "keywords/sentinel"
    }
  ],
  "weapons": [
    {
      "name": "E-22 Blaster Rifle",
      "range": {
        "min": 0,
        "max": 3
      },
      "dice": {
        "black": 1
      },
      "keywords": []
    },
    {
      "name": "DF-90 Mortar",
      "range": {
        "min": 3,
        "max": 4
      },
      "dice": {
        "white": 3
      },
      "keywords": [
        {
          "ref": "keywords/fixed_front"
        },
        {
          "ref": "keywords/critical_1"
        },
        {
          "ref": "keywords/cumbersome"
        },
        {
          "ref": "keywords/suppressive"
        }
      ]
    }
  ],
  "upgrade_slots": [
    "Comms"
  ]
}
