{
  "name": "Moff Gideon",
  "title": "Long Live the Empire",
  "faction": "Galactic Empire",
  "rank": "Commander",
  "unit_type": "Trooper",
  "squad_size": 1,
  "stats": {
    "health": 5,
    "courage": 3,
    "speed": 2,
    "defense_die": "Red",
    "surges": {
      "attack": "Critical",
      "defense": "Block"
    }
  },
  "keywords": [
    {
      "ref": "keywords/observe_1"
    },
    {
      "ref": "keywords/entourage_imperial_dark_troopers"
    },
    {
      "ref": "keywords/ruthless"
    },
    {
      "ref": "keywords/sharpshooter_1"
    },
    {
      "ref": "keywords/tactical_1"
    }
  ],
  "weapons": [
    {
      "name": "Combat Training",
      "range": {
        "min": 0,
        "max": 0
      },
      "dice": {
        "red": 2
      },
      "keywords": []
    },
    {
      "name": "Gideon's Blaster",
      "range": {
        "min": 1,
        "max": 2
      },
      "dice": {
        "red": 1,
        "black": 2
      },
      "keywords": [
        {
          "ref": "keywords/pierce_1"
        }
      ]
    }
  ],
  "upgrade_slots": [
    "Command",
    "Command",
    "Training",
    "Gear",
    "Armament"
  ]
}
